{
  "project_info": {
    "project_number": "260849137592",
    "project_id": "fruits-market-613e5",
    "storage_bucket": "fruits-market-613e5.firebasestorage.app"
  },
  "client": [
    {
      "client_info": {
        "mobilesdk_app_id": "1:260849137592:android:f0142904b9b6635b01814d",
        "android_client_info": {
          "package_name": "com.example.fruits_hub"
        }
      },
      "oauth_client": [
        {
          "client_id": "260849137592-2jk7qadqqs5tpni34s3hmievb18t5itm.apps.googleusercontent.com",
          "client_type": 3
        }
      ],
      "api_key": [
        {
          "current_key": "AIzaSyCuSF1kwGbltWzrkuVd-x14k31D5kRTF_s"
        }
      ],
      "services": {
        "appinvite_service": {
          "other_platform_oauth_client": [
            {
              "client_id": "260849137592-2jk7qadqqs5tpni34s3hmievb18t5itm.apps.googleusercontent.com",
              "client_type": 3
            },
            {
              "client_id": "260849137592-2njit29lc2eq70p0narji5iq62n0q1k3.apps.googleusercontent.com",
              "client_type": 2,
              "ios_info": {
                "bundle_id": "com.example.fruitshubDashboard"
              }
            }
          ]
        }
      }
    },
    {
      "client_info": {
        "mobilesdk_app_id": "1:260849137592:android:6803a3147005dff701814d",
        "android_client_info": {
          "package_name": "com.example.fruitshub_dashboard"
        }
      },
      "oauth_client": [
        {
          "client_id": "260849137592-2jk7qadqqs5tpni34s3hmievb18t5itm.apps.googleusercontent.com",
          "client_type": 3
        }
      ],
      "api_key": [
        {
          "current_key": "AIzaSyCuSF1kwGbltWzrkuVd-x14k31D5kRTF_s"
        }
      ],
      "services": {
        "appinvite_service": {
          "other_platform_oauth_client": [
            {
              "client_id": "260849137592-2jk7qadqqs5tpni34s3hmievb18t5itm.apps.googleusercontent.com",
              "client_type": 3
            },
            {
              "client_id": "260849137592-2njit29lc2eq70p0narji5iq62n0q1k3.apps.googleusercontent.com",
              "client_type": 2,
              "ios_info": {
                "bundle_id": "com.example.fruitshubDashboard"
              }
            }
          ]
        }
      }
    }
  ],
  "configuration_version": "1"
}